{
    "sourceFile": ".env.local",
    "activeCommit": 0,
    "commits": [
        {
            "activePatchIndex": 16,
            "patches": [
                {
                    "date": 1746891704089,
                    "content": "Index: \n===================================================================\n--- \n+++ \n"
                },
                {
                    "date": 1746904766689,
                    "content": "Index: \n===================================================================\n--- \n+++ \n@@ -1,5 +1,7 @@\n MONGODB_URI=mongodb+srv://dlicht03:Licht03@cluster0.vjld3aw.mongodb.net/aish_store?retryWrites=true&w=majority&appName=Cluster0\n NEXTAUTH_URL=http://localhost:3000\n-NEXTAUTH_SECRET=your-secret-key-here\n+NEXTAUTH_SECRET=030102030102\n ADMIN_USERNAME=admin\n\\ No newline at end of file\n-ADMIN_PASSWORD=Licht03\n+ADMIN_PASSWORD=Licht03\n+GOOGLE_CLIENT_ID=553851564585-59sop7ekkcsp9262o6ct3hgmpc58h3re.apps.googleusercontent.com\n+GOOGLE_CLIENT_SECRET=... (dán Client Secret vào đây)\n\\ No newline at end of file\n"
                },
                {
                    "date": 1746904929862,
                    "content": "Index: \n===================================================================\n--- \n+++ \n@@ -3,5 +3,5 @@\n NEXTAUTH_SECRET=030102030102\n ADMIN_USERNAME=admin\n ADMIN_PASSWORD=Licht03\n GOOGLE_CLIENT_ID=553851564585-59sop7ekkcsp9262o6ct3hgmpc58h3re.apps.googleusercontent.com\n-GOOGLE_CLIENT_SECRET=... (dán Client Secret vào đây)\n\\ No newline at end of file\n+GOOGLE_CLIENT_SECRET=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\n\\ No newline at end of file\n"
                },
                {
                    "date": 1746904990696,
                    "content": "Index: \n===================================================================\n--- \n+++ \n@@ -1,7 +1,7 @@\n MONGODB_URI=mongodb+srv://dlicht03:Licht03@cluster0.vjld3aw.mongodb.net/aish_store?retryWrites=true&w=majority&appName=Cluster0\n NEXTAUTH_URL=http://localhost:3000\n-NEXTAUTH_SECRET=030102030102\n+NEXTAUTH_SECRET=https://generate-secret.vercel.app/32\n ADMIN_USERNAME=admin\n ADMIN_PASSWORD=Licht03\n GOOGLE_CLIENT_ID=553851564585-59sop7ekkcsp9262o6ct3hgmpc58h3re.apps.googleusercontent.com\n GOOGLE_CLIENT_SECRET=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\n\\ No newline at end of file\n"
                },
                {
                    "date": 1746953771760,
                    "content": "Index: \n===================================================================\n--- \n+++ \n@@ -2,6 +2,6 @@\n NEXTAUTH_URL=http://localhost:3000\n NEXTAUTH_SECRET=https://generate-secret.vercel.app/32\n ADMIN_USERNAME=admin\n ADMIN_PASSWORD=Licht03\n-GOOGLE_CLIENT_ID=553851564585-59sop7ekkcsp9262o6ct3hgmpc58h3re.apps.googleusercontent.com\n+GOOGLE_CLIENT_ID=360693986418-sucnvkqf9qfe9f63ncmtechl4b85uj5p.apps.googleusercontent.com\n GOOGLE_CLIENT_SECRET=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\n\\ No newline at end of file\n"
                },
                {
                    "date": 1746953846498,
                    "content": "Index: \n===================================================================\n--- \n+++ \n@@ -0,0 +1,7 @@\n+MONGODB_URI=mongodb+srv://dlicht03:Licht03@cluster0.vjld3aw.mongodb.net/aish_store?retryWrites=true&w=majority&appName=Cluster0\n+NEXTAUTH_URL=http://localhost:3000\n+NEXTAUTH_SECRET=https://generate-secret.vercel.app/32\n+ADMIN_USERNAME=admin\n+ADMIN_PASSWORD=Licht03\n+GOOGLE_CLIENT_ID=360693986418-sucnvkqf9qfe9f63ncmtechl4b85uj5p.apps.googleusercontent.com\n+GOOGLE_CLIENT_SECRET=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\n\\ No newline at end of file\n"
                },
                {
                    "date": 1746954251516,
                    "content": "Index: \n===================================================================\n--- \n+++ \n@@ -2,13 +2,6 @@\n NEXTAUTH_URL=http://localhost:3000\n NEXTAUTH_SECRET=https://generate-secret.vercel.app/32\n ADMIN_USERNAME=admin\n ADMIN_PASSWORD=Licht03\n-GOOGLE_CLIENT_ID=360693986418-sucnvkqf9qfe9f63ncmtechl4b85uj5p.apps.googleusercontent.com\n-GOOGLE_CLIENT_SECRET=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\n-MONGODB_URI=mongodb+srv://dlicht03:Licht03@cluster0.vjld3aw.mongodb.net/aish_store?retryWrites=true&w=majority&appName=Cluster0\n-NEXTAUTH_URL=http://localhost:3000\n-NEXTAUTH_SECRET=https://generate-secret.vercel.app/32\n-ADMIN_USERNAME=admin\n-ADMIN_PASSWORD=Licht03\n-GOOGLE_CLIENT_ID=360693986418-sucnvkqf9qfe9f63ncmtechl4b85uj5p.apps.googleusercontent.com\n-GOOGLE_CLIENT_SECRET=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\n\\ No newline at end of file\n+GOOGLE_CLIENT_ID=133301315818-4c6vrtpq2lhfss22sq2po6pikpvc8qvc.apps.googleusercontent.com\n+GOOGLE_CLIENT_SECRET=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\n\\ No newline at end of file\n"
                },
                {
                    "date": 1746954266398,
                    "content": "Index: \n===================================================================\n--- \n+++ \n@@ -3,5 +3,5 @@\n NEXTAUTH_SECRET=https://generate-secret.vercel.app/32\n ADMIN_USERNAME=admin\n ADMIN_PASSWORD=Licht03\n GOOGLE_CLIENT_ID=133301315818-4c6vrtpq2lhfss22sq2po6pikpvc8qvc.apps.googleusercontent.com\n-GOOGLE_CLIENT_SECRET=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\n\\ No newline at end of file\n+GOOGLE_CLIENT_SECRET=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\n\\ No newline at end of file\n"
                },
                {
                    "date": 1746957723678,
                    "content": "Index: \n===================================================================\n--- \n+++ \n@@ -3,5 +3,6 @@\n NEXTAUTH_SECRET=https://generate-secret.vercel.app/32\n ADMIN_USERNAME=admin\n ADMIN_PASSWORD=Licht03\n GOOGLE_CLIENT_ID=133301315818-4c6vrtpq2lhfss22sq2po6pikpvc8qvc.apps.googleusercontent.com\n-GOOGLE_CLIENT_SECRET=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\n\\ No newline at end of file\n+GOOGLE_CLIENT_SECRET=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\n+NEXT_PUBLIC_ADMIN_EMAIL=dlicht02@gmail.com\n\\ No newline at end of file\n"
                },
                {
                    "date": 1747240821067,
                    "content": "Index: \n===================================================================\n--- \n+++ \n@@ -1,8 +1,10 @@\n MONGODB_URI=mongodb+srv://dlicht03:Licht03@cluster0.vjld3aw.mongodb.net/aish_store?retryWrites=true&w=majority&appName=Cluster0\n NEXTAUTH_URL=http://localhost:3000\n-NEXTAUTH_SECRET=https://generate-secret.vercel.app/32\n+NEXTAUTH_SECRET=32\n ADMIN_USERNAME=admin\n ADMIN_PASSWORD=Licht03\n GOOGLE_CLIENT_ID=133301315818-4c6vrtpq2lhfss22sq2po6pikpvc8qvc.apps.googleusercontent.com\n GOOGLE_CLIENT_SECRET=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\n\\ No newline at end of file\n-NEXT_PUBLIC_ADMIN_EMAIL=dlicht02@gmail.com\n+NEXT_PUBLIC_ADMIN_EMAIL=dlicht02@gmail.com\n+EMAIL_USER=dlicht03@gmail.comcom\n+EMAIL_APP_PASSWORD=dgyg wgrr fiap lnuk\n"
                },
                {
                    "date": 1747240840986,
                    "content": "Index: \n===================================================================\n--- \n+++ \n@@ -4,7 +4,7 @@\n ADMIN_USERNAME=admin\n ADMIN_PASSWORD=Licht03\n GOOGLE_CLIENT_ID=133301315818-4c6vrtpq2lhfss22sq2po6pikpvc8qvc.apps.googleusercontent.com\n GOOGLE_CLIENT_SECRET=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\n-NEXT_PUBLIC_ADMIN_EMAIL=dlicht02@gmail.com\n+NEXT_PUBLIC_ADMIN_EMAIL=dlicht03@gmail.com\n EMAIL_USER=dlicht03@gmail.comcom\n\\ No newline at end of file\n-EMAIL_APP_PASSWORD=dgyg wgrr fiap lnuk\n+EMAIL_APP_PASSWORD=dgyg wgrr fiap lnuk\n"
                },
                {
                    "date": 1747240846847,
                    "content": "Index: \n===================================================================\n--- \n+++ \n@@ -4,7 +4,7 @@\n ADMIN_USERNAME=admin\n ADMIN_PASSWORD=Licht03\n GOOGLE_CLIENT_ID=133301315818-4c6vrtpq2lhfss22sq2po6pikpvc8qvc.apps.googleusercontent.com\n GOOGLE_CLIENT_SECRET=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\n-NEXT_PUBLIC_ADMIN_EMAIL=dlicht03@gmail.com\n+NEXT_PUBLIC_ADMIN_EMAIL=dlicht02@gmail.com\n EMAIL_USER=dlicht03@gmail.comcom\n\\ No newline at end of file\n-EMAIL_APP_PASSWORD=dgyg wgrr fiap lnuk\n+EMAIL_APP_PASSWORD=dgyg wgrr fiap lnuk\n"
                },
                {
                    "date": 1747240846882,
                    "content": "Index: \n===================================================================\n--- \n+++ \n@@ -6,5 +6,5 @@\n GOOGLE_CLIENT_ID=133301315818-4c6vrtpq2lhfss22sq2po6pikpvc8qvc.apps.googleusercontent.com\n GOOGLE_CLIENT_SECRET=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\n NEXT_PUBLIC_ADMIN_EMAIL=dlicht02@gmail.com\n EMAIL_USER=dlicht03@gmail.comcom\n-EMAIL_APP_PASSWORD=dgyg wgrr fiap lnuk\n\\ No newline at end of file\n+EMAIL_APP_PASSWORD=dgyg wgrr fiap lnuk\n"
                },
                {
                    "date": 1747241118994,
                    "content": "Index: \n===================================================================\n--- \n+++ \n@@ -6,5 +6,5 @@\n GOOGLE_CLIENT_ID=133301315818-4c6vrtpq2lhfss22sq2po6pikpvc8qvc.apps.googleusercontent.com\n GOOGLE_CLIENT_SECRET=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\n NEXT_PUBLIC_ADMIN_EMAIL=dlicht02@gmail.com\n EMAIL_USER=dlicht03@gmail.comcom\n-EMAIL_APP_PASSWORD=dgyg wgrr fiap lnuk\n+EMAIL_APP_PASSWORD=mczi ybrw bjgg yimt\n"
                },
                {
                    "date": 1747241703945,
                    "content": "Index: \n===================================================================\n--- \n+++ \n@@ -5,6 +5,6 @@\n ADMIN_PASSWORD=Licht03\n GOOGLE_CLIENT_ID=133301315818-4c6vrtpq2lhfss22sq2po6pikpvc8qvc.apps.googleusercontent.com\n GOOGLE_CLIENT_SECRET=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\n NEXT_PUBLIC_ADMIN_EMAIL=dlicht02@gmail.com\n-EMAIL_USER=dlicht03@gmail.comcom\n+EMAIL_USER=dlicht03@gmail.com\n EMAIL_APP_PASSWORD=mczi ybrw bjgg yimt\n"
                },
                {
                    "date": 1747241921604,
                    "content": "Index: \n===================================================================\n--- \n+++ \n@@ -5,6 +5,6 @@\n ADMIN_PASSWORD=Licht03\n GOOGLE_CLIENT_ID=133301315818-4c6vrtpq2lhfss22sq2po6pikpvc8qvc.apps.googleusercontent.com\n GOOGLE_CLIENT_SECRET=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\n NEXT_PUBLIC_ADMIN_EMAIL=dlicht02@gmail.com\n-EMAIL_USER=dlicht03@gmail.com\n+EMAIL_USER=aish.aish.vn@gmail.com\n EMAIL_APP_PASSWORD=mczi ybrw bjgg yimt\n"
                },
                {
                    "date": 1747242201136,
                    "content": "Index: \n===================================================================\n--- \n+++ \n@@ -6,5 +6,5 @@\n GOOGLE_CLIENT_ID=133301315818-4c6vrtpq2lhfss22sq2po6pikpvc8qvc.apps.googleusercontent.com\n GOOGLE_CLIENT_SECRET=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\n NEXT_PUBLIC_ADMIN_EMAIL=dlicht02@gmail.com\n EMAIL_USER=aish.aish.vn@gmail.com\n-EMAIL_APP_PASSWORD=mczi ybrw bjgg yimt\n+EMAIL_APP_PASSWORD=tnpp rbje cizl xwxg\n"
                }
            ],
            "date": 1746891704042,
            "name": "cart",
            "content": "MONGODB_URI=mongodb+srv://dlicht03:Licht03@cluster0.vjld3aw.mongodb.net/aish_store?retryWrites=true&w=majority&appName=Cluster0\nNEXTAUTH_URL=http://localhost:3000\nNEXTAUTH_SECRET=your-secret-key-here\nADMIN_USERNAME=admin\nADMIN_PASSWORD=Licht03"
        }
    ]
}