{
    "sourceFile": "src/i18n.js",
    "activeCommit": 0,
    "commits": [
        {
            "activePatchIndex": 0,
            "patches": [
                {
                    "date": 1747292757117,
                    "content": "Index: \n===================================================================\n--- \n+++ \n"
                }
            ],
            "date": 1747292757117,
            "name": "Commit-0",
            "content": "const i18n = {\r\n  en: {\r\n    \"common.english\": \"ENGLISH\",\r\n    \"common.vietnamese\": \"VIETNAMESE\",\r\n    \"common.contact\": \"CONTACT US\",\r\n    \"common.follow\": \"FOLLOW US\",\r\n    \"common.service\": \"SERVICE\",\r\n    \"common.about\": \"ABOUT AISH\",\r\n    \"common.language\": \"LANGUAGE\",\r\n    \"common.returnPolicy\": \"RETURN POLICY\",\r\n    \"common.warrantyPolicy\": \"WARRANTY POLICY\",\r\n    \"common.careInstructions\": \"CARE INSTRUCTIONS\",\r\n  },\r\n  vi: {\r\n    \"common.english\": \"TIẾNG ANH\",\r\n    \"common.vietnamese\": \"TIẾNG VIỆT\",\r\n    \"common.contact\": \"LIÊN HỆ\",\r\n    \"common.follow\": \"THEO DÕI\",\r\n    \"common.service\": \"DỊCH VỤ\",\r\n    \"common.about\": \"VỀ AISH\",\r\n    \"common.language\": \"NGÔN NGỮ\",\r\n    \"common.returnPolicy\": \"CHÍNH SÁCH ĐỔI TRẢ\",\r\n    \"common.warrantyPolicy\": \"CHÍNH SÁCH BẢO HÀNH\",\r\n    \"common.careInstructions\": \"HƯỚNG DẪN BẢO QUẢN\",\r\n  },\r\n};\r\n\r\nexport default i18n; "
        }
    ]
}